naga/__init__.py
naga/lazy_seq.py
naga/persistent_vector.py
naga/precompyled.py
naga/tools.py
naga/utils.py
naga-0.2.6.7.dist-info/DESCRIPTION.rst
naga-0.2.6.7.dist-info/METADATA
naga-0.2.6.7.dist-info/RECORD
naga-0.2.6.7.dist-info/WHEEL
naga-0.2.6.7.dist-info/metadata.json
naga-0.2.6.7.dist-info/top_level.txt
