Metadata-Version: 2.0
Name: naga
Version: 0.2.6.7
Summary: A powerful Clojure-inspired Python/Lisp-hybrid-monster!
Home-page: https://github.com/hiimjayhireme/naga
Author: James J. Tolton
Author-email: jjtolton@gmail.com
License: UNKNOWN
Keywords: lisp,clojure,functional,fp
Platform: UNKNOWN
